README.md
setup.cfg
setup.py
network_utils/__init__.py
network_utils/networklibs.py
network_utils.egg-info/PKG-INFO
network_utils.egg-info/SOURCES.txt
network_utils.egg-info/dependency_links.txt
network_utils.egg-info/not-zip-safe
network_utils.egg-info/top_level.txt