Metadata-Version: 2.1
Name: network-utils
Version: 1.0
Summary: Helpful tools for building socket applications
Home-page: UNKNOWN
Author-email: leroy.ryan09@gmail.com
License: UNKNOWN
Platform: UNKNOWN
